[
  {
    "id": "abb29608-633e-48c4-ab72-60689cb240c1",
    "tenant_id": "tenant-1",
    "timestamp": "2026-03-19T02:24:36.002082247Z",
    "event_type": "user_management",
    "action": "create_role",
    "user_id": "system",
    "user_type": "human",
    "resource_type": "role",
    "resource_id": "tenant1.role",
    "resource_name": "Tenant 1 Role",
    "result": "success",
    "details": {
      "role_description": "Role for tenant 1",
      "role_permissions": 0
    },
    "severity": "high",
    "source": "rbac",
    "version": "1.0",
    "checksum": "9e5ea0974fd8fceee5d9992854f91962f3ffa9de72ce549694828f47f9b8634f"
  }
]